{
  "__id": "08de2b40-77bf-5d1b-8469-a7475d18b5a8",
  "name": "Заявления на присвоение категории",
  "namespace": "kedo",
  "code": "application_category_assignment",
  "type": "APPLICATION",
  "icon": "file_type_text",
  "sort": 38,
  "system": false,
  "hidden": false,
  "data": {
    "openInNewTab": false,
    "widgets": [
      {
        "type": "appview",
        "customWidgetId": "",
        "template": null,
        "data": {
          "pageCode": "application_category_assignment",
          "namespaceCode": "kedo"
        }
      }
    ],
    "menu": {
      "type": "namespace"
    },
    "columns": 1,
    "layout": "table",
    "description": ""
  },
  "recoveryWithParent": false,
  "navigation": null,
  "__createdAt": "2023-12-20T13:07:52.400261Z",
  "__updatedAt": "2024-02-14T11:11:39.983890758Z",
  "__deletedAt": null,
  "__createdBy": "7303b866-4220-4086-a09e-348a76b12c73",
  "__updatedBy": "7303b866-4220-4086-a09e-348a76b12c73",
  "editions": null,
  "solution": "saas"
}
