{
  "__id": "aff3dccc-ab69-5710-ab91-5006ab37517e",
  "namespace": "kedo",
  "code": "5d5c4eba-6ce2-4e48-a831-b84a42152526",
  "__name": "Доступы для Предложение в график отпусков ЭЛМА",
  "description": "018c8c85-19ee-7ff5-8e5a-de106dd4e3c5",
  "isDefault": false,
  "isRole": false,
  "privileges": ["system"],
  "subOrgunitIds": null,
  "__createdAt": "2024-03-22T07:21:41.626369074Z",
  "__updatedAt": "2024-03-22T07:21:41.626369074Z",
  "__deletedAt": null,
  "__createdBy": "d4c0aacb-19ed-44fa-b229-5f7ed736889c",
  "__updatedBy": "d4c0aacb-19ed-44fa-b229-5f7ed736889c",
  "integration": null,
  "readonly": false
}
