{
  "__id": "cdb80d20-091e-5459-94a9-e8c37649b20a",
  "namespace": "kedo",
  "code": "a14cf9ca-f8e4-4fdb-854d-a818305f8990",
  "__name": "Доступы для На командировку ЭЛМА2",
  "description": "018d82ba-b430-783f-ae3f-d6a1a2e73a7b",
  "isDefault": false,
  "isRole": false,
  "privileges": ["system"],
  "subOrgunitIds": null,
  "__createdAt": "2024-03-22T07:22:02.924163718Z",
  "__updatedAt": "2024-03-22T07:22:02.924163718Z",
  "__deletedAt": null,
  "__createdBy": "d4c0aacb-19ed-44fa-b229-5f7ed736889c",
  "__updatedBy": "d4c0aacb-19ed-44fa-b229-5f7ed736889c",
  "integration": null,
  "readonly": false
}
