{
  "__id": "09f11135-99e8-5413-bae7-4ffa590b5021",
  "namespace": "kedo",
  "code": "eb70345a-5a40-4a19-afda-8f7798428cf1",
  "__name": "Доступы для Личные документы Крон-Ц. Филиал в г. Волгоград",
  "description": "018c8c27-6833-7ff4-b880-e4eb327764f2",
  "isDefault": false,
  "isRole": false,
  "privileges": ["system"],
  "subOrgunitIds": null,
  "__createdAt": "2024-03-22T07:20:32.788539254Z",
  "__updatedAt": "2024-03-22T07:20:32.788539254Z",
  "__deletedAt": null,
  "__createdBy": "d4c0aacb-19ed-44fa-b229-5f7ed736889c",
  "__updatedBy": "d4c0aacb-19ed-44fa-b229-5f7ed736889c",
  "integration": null,
  "readonly": false
}
